LICENSE
MANIFEST.in
README.rst
setup.py
bestway/__init__.py
bestway.egg-info/PKG-INFO
bestway.egg-info/SOURCES.txt
bestway.egg-info/dependency_links.txt
bestway.egg-info/top_level.txt