Metadata-Version: 2.1
Name: bestway
Version: 0.1.1
Summary: UNKNOWN
Home-page: http://github.com/d4v1ncy/bestway
Author: Ð4√¡η¢Ч
Author-email: d4v1ncy@protonmail.ch
License: UNKNOWN
Platform: UNKNOWN
Classifier: Development Status :: 1 - Planning
Classifier: License :: OSI Approved :: The Unlicense (Unlicense)
Classifier: Operating System :: POSIX
Classifier: Programming Language :: Python :: 3
License-File: LICENSE
